[{"id":"2f3e077d.bf3588","type":"ibmiot in","z":"1824fe2d.71b782","authentication":"apiKey","apiKey":"d73e9298.132af","inputType":"evt","logicalInterface":"","ruleId":"","deviceId":"1","applicationId":"","deviceType":"absolute","eventType":"+","commandType":"","format":"json","name":"IBM IoT","service":"registered","allDevices":false,"allApplications":"","allDeviceTypes":false,"allLogicalInterfaces":"","allEvents":true,"allCommands":"","allFormats":"","qos":0,"x":220,"y":160,"wires":[["15b174f9.22bd4b","847c5e40.96315","f70565db.ab4388","84f802cd.13cd6","9ea812ad.05896","d46bcfa1.6d5cf","252ef798.f91ea8"]]},{"id":"d73e9298.132af","type":"ibmiot","z":"","name":"NODE","keepalive":"60","serverName":"lz8w35.messaging.internetofthings.ibmcloud.com","cleansession":true,"appId":"","shared":false}]